smyte
