Metadata-Version: 1.0
Name: Smyte
Version: 0.1.2
Summary: Smyte client library for Python
Home-page: UNKNOWN
Author: Pete Hunt
Author-email: UNKNOWN
License: UNKNOWN
Platform: UNKNOWN
